{"date": "2019-01-22", "split": "legs", "exercises": {"leg extention": [{"set no.": 1, "reps": 2, "weight": "71.97999999999993 kg"}, {"set no.": 2, "reps": 4, "weight": "67.93199999999993 kg"}, {"set no.": 3, "reps": 4, "weight": "69.02799999999992 kg"}, {"set no.": 4, "reps": 8, "weight": "62.575999999999915 kg"}, {"set no.": 5, "reps": 9, "weight": "60.27799999999992 kg"}], "squat": [{"set no.": 1, "reps": 3, "weight": "116.47999999999993 kg"}, {"set no.": 2, "reps": 5, "weight": "110.47999999999993 kg"}, {"set no.": 3, "reps": 12, "weight": "88.38399999999994 kg"}, {"set no.": 4, "reps": 2, "weight": "118.93199999999993 kg"}], "hamstring curl": [{"set no.": 1, "reps": 5, "weight": "44.854999999999926 kg"}, {"set no.": 2, "reps": 19, "weight": "30.20099999999991 kg"}, {"set no.": 3, "reps": 4, "weight": "47.075999999999915 kg"}, {"set no.": 4, "reps": 15, "weight": "34.15299999999992 kg"}, {"set no.": 5, "reps": 4, "weight": "45.43199999999993 kg"}, {"set no.": 6, "reps": 20, "weight": "27.431999999999935 kg"}], "legpress": [{"set no.": 1, "reps": 9, "weight": "99.57599999999991 kg"}], "barbell lunge": [{"set no.": 1, "reps": 1, "weight": "72.63399999999994 kg"}, {"set no.": 2, "reps": 7, "weight": "63.77799999999992 kg"}, {"set no.": 3, "reps": 2, "weight": "72.52799999999992 kg"}, {"set no.": 4, "reps": 15, "weight": "49.229999999999926 kg"}], "deadlift": [{"set no.": 1, "reps": 15, "weight": "81.57599999999991 kg"}, {"set no.": 2, "reps": 15, "weight": "81.57599999999991 kg"}, {"set no.": 3, "reps": 14, "weight": "82.38399999999994 kg"}, {"set no.": 4, "reps": 8, "weight": "100.93199999999993 kg"}, {"set no.": 5, "reps": 11, "weight": "91.38399999999994 kg"}]}}