{"date": "2019-07-25", "split": "shoulders", "exercises": {"rear laterals": [{"set no.": 1, "reps": 17, "weight": "28.258823529411767 kg"}, {"set no.": 2, "reps": 3, "weight": "35.583333333333336 kg"}, {"set no.": 3, "reps": 6, "weight": "28.533333333333335 kg"}, {"set no.": 4, "reps": 17, "weight": "38.9514705882353 kg"}, {"set no.": 5, "reps": 11, "weight": "35.43181818181818 kg"}, {"set no.": 6, "reps": 9, "weight": "42.41111111111111 kg"}], "side laterals": [{"set no.": 1, "reps": 12, "weight": "39.10833333333334 kg"}, {"set no.": 2, "reps": 20, "weight": "35.55 kg"}, {"set no.": 3, "reps": 7, "weight": "43.15714285714285 kg"}, {"set no.": 4, "reps": 7, "weight": "29.485714285714288 kg"}, {"set no.": 5, "reps": 1, "weight": "37.25 kg"}], "cable crossover": [{"set no.": 1, "reps": 20, "weight": "28.400000000000002 kg"}, {"set no.": 2, "reps": 7, "weight": "43.15714285714285 kg"}, {"set no.": 3, "reps": 10, "weight": "35.75 kg"}]}}