{"date": "2021-11-18", "split": "legs", "exercises": {"barbell_lunge": [{"set no.": 1, "reps": 11, "weight": "202.49 kg"}, {"set no.": 2, "reps": 19, "weight": "146.63 kg"}, {"set no.": 3, "reps": 18, "weight": "153.23 kg"}], "deadlift": [{"set no.": 1, "reps": 18, "weight": "264.00 kg"}, {"set no.": 2, "reps": 12, "weight": "334.32 kg"}, {"set no.": 3, "reps": 13, "weight": "324.00 kg"}, {"set no.": 4, "reps": 6, "weight": "406.98 kg"}, {"set no.": 5, "reps": 18, "weight": "263.34 kg"}], "standing_calf_raise": [{"set no.": 1, "reps": 2, "weight": "114.00 kg"}], "legpress": [{"set no.": 1, "reps": 13, "weight": "324.00 kg"}, {"set no.": 2, "reps": 2, "weight": "454.86 kg"}, {"set no.": 3, "reps": 1, "weight": "465.66 kg"}, {"set no.": 4, "reps": 20, "weight": "240.00 kg"}], "squat": [{"set no.": 1, "reps": 4, "weight": "432.00 kg"}], "leg_extention": [{"set no.": 1, "reps": 16, "weight": "167.16 kg"}, {"set no.": 2, "reps": 12, "weight": "195.02 kg"}, {"set no.": 3, "reps": 2, "weight": "264.67 kg"}]}}