{"date": "2020-02-28", "split": "shoulders", "exercises": {"front_laterals": [{"set no.": 1, "reps": 2, "weight": "15.31 kg"}, {"set no.": 2, "reps": 1, "weight": "15.56 kg"}, {"set no.": 3, "reps": 6, "weight": "14.31 kg"}], "dumbbell_military_press": [{"set no.": 1, "reps": 10, "weight": "17.81 kg"}, {"set no.": 2, "reps": 4, "weight": "20.21 kg"}, {"set no.": 3, "reps": 2, "weight": "21.01 kg"}, {"set no.": 4, "reps": 9, "weight": "18.21 kg"}, {"set no.": 5, "reps": 5, "weight": "19.81 kg"}], "cable_crossover": [{"set no.": 1, "reps": 7, "weight": "12.41 kg"}, {"set no.": 2, "reps": 9, "weight": "12.01 kg"}], "side_laterals": [{"set no.": 1, "reps": 10, "weight": "13.31 kg"}, {"set no.": 2, "reps": 4, "weight": "14.81 kg"}, {"set no.": 3, "reps": 9, "weight": "13.56 kg"}, {"set no.": 4, "reps": 2, "weight": "15.31 kg"}, {"set no.": 5, "reps": 8, "weight": "13.81 kg"}], "arnold_press": [{"set no.": 1, "reps": 8, "weight": "18.61 kg"}, {"set no.": 2, "reps": 7, "weight": "19.01 kg"}, {"set no.": 3, "reps": 7, "weight": "19.01 kg"}, {"set no.": 4, "reps": 1, "weight": "21.41 kg"}, {"set no.": 5, "reps": 8, "weight": "18.61 kg"}, {"set no.": 6, "reps": 3, "weight": "20.61 kg"}]}}