{"date": "2021-04-11", "split": "legs", "exercises": {"leg extention": [{"set no.": 1, "reps": 18, "weight": "124.1138888888889 kg"}], "squat": [{"set no.": 1, "reps": 13, "weight": "127.34038461538462 kg"}, {"set no.": 2, "reps": 8, "weight": "156.9 kg"}], "barbell lunge": [{"set no.": 1, "reps": 16, "weight": "137.3125 kg"}], "legpress": [{"set no.": 1, "reps": 17, "weight": "111.31764705882354 kg"}, {"set no.": 2, "reps": 5, "weight": "133.925 kg"}, {"set no.": 3, "reps": 5, "weight": "122.80000000000001 kg"}, {"set no.": 4, "reps": 14, "weight": "111.9857142857143 kg"}], "seated calf raise": [{"set no.": 1, "reps": 8, "weight": "123.47500000000001 kg"}, {"set no.": 2, "reps": 19, "weight": "162.66842105263157 kg"}], "standing calf raise": [{"set no.": 1, "reps": 13, "weight": "162.99230769230766 kg"}]}}