{"date": "2020-07-28", "split": "legs", "exercises": {"leg extention": [{"set no.": 1, "reps": 2, "weight": "106.5 kg"}, {"set no.": 2, "reps": 16, "weight": "91.0625 kg"}, {"set no.": 3, "reps": 6, "weight": "102.68333333333334 kg"}, {"set no.": 4, "reps": 3, "weight": "122.86666666666667 kg"}, {"set no.": 5, "reps": 14, "weight": "99.49285714285715 kg"}, {"set no.": 6, "reps": 9, "weight": "82.98333333333333 kg"}], "hamstring curl": [{"set no.": 1, "reps": 20, "weight": "98.9 kg"}, {"set no.": 2, "reps": 11, "weight": "89.4090909090909 kg"}], "squat": [{"set no.": 1, "reps": 20, "weight": "83.9 kg"}, {"set no.": 2, "reps": 13, "weight": "113.8923076923077 kg"}, {"set no.": 3, "reps": 19, "weight": "83.28157894736843 kg"}]}}