{"date": "2019-02-19", "split": "chest", "exercises": {"barbell_bench_press": [{"set no.": 1, "reps": 4, "weight": "87.00 kg"}, {"set no.": 2, "reps": 5, "weight": "84.75 kg"}, {"set no.": 3, "reps": 5, "weight": "84.75 kg"}, {"set no.": 4, "reps": 4, "weight": "87.00 kg"}, {"set no.": 5, "reps": 6, "weight": "82.50 kg"}, {"set no.": 6, "reps": 7, "weight": "80.25 kg"}], "barbell_incline_press": [{"set no.": 1, "reps": 3, "weight": "70.75 kg"}, {"set no.": 2, "reps": 5, "weight": "67.25 kg"}, {"set no.": 3, "reps": 7, "weight": "63.75 kg"}, {"set no.": 4, "reps": 6, "weight": "65.50 kg"}], "dip": [{"set no.": 1, "reps": 2, "weight": "10.75 kg"}, {"set no.": 2, "reps": 1, "weight": "10.88 kg"}, {"set no.": 3, "reps": 9, "weight": "9.88 kg"}]}}