{"date": "2018-05-02", "split": "chest", "exercises": {"dumbbell_fly": [{"set no.": 1, "reps": 6, "weight": "21.19 kg"}, {"set no.": 2, "reps": 5, "weight": "21.64 kg"}, {"set no.": 3, "reps": 5, "weight": "21.64 kg"}, {"set no.": 4, "reps": 9, "weight": "19.84 kg"}, {"set no.": 5, "reps": 10, "weight": "19.39 kg"}, {"set no.": 6, "reps": 1, "weight": "23.44 kg"}], "barbell_incline_press": [{"set no.": 1, "reps": 10, "weight": "58.39 kg"}], "cable_crossover": [{"set no.": 1, "reps": 2, "weight": "39.14 kg"}, {"set no.": 2, "reps": 5, "weight": "36.51 kg"}, {"set no.": 3, "reps": 7, "weight": "34.76 kg"}, {"set no.": 4, "reps": 3, "weight": "38.26 kg"}], "dip": [{"set no.": 1, "reps": 10, "weight": "9.64 kg"}], "dumbbell_pullover": [{"set no.": 1, "reps": 9, "weight": "29.14 kg"}, {"set no.": 2, "reps": 5, "weight": "32.14 kg"}], "barbell_bench_press": [{"set no.": 1, "reps": 2, "weight": "91.39 kg"}, {"set no.": 2, "reps": 10, "weight": "73.39 kg"}, {"set no.": 3, "reps": 5, "weight": "84.64 kg"}, {"set no.": 4, "reps": 6, "weight": "82.39 kg"}, {"set no.": 5, "reps": 3, "weight": "89.14 kg"}]}}