{"date": "2021-04-14", "split": "chest", "exercises": {"cable_crossover": [{"set no.": 1, "reps": 19, "weight": "24.72 kg"}, {"set no.": 2, "reps": 14, "weight": "30.50 kg"}, {"set no.": 3, "reps": 12, "weight": "30.14 kg"}, {"set no.": 4, "reps": 4, "weight": "37.84 kg"}], "dip": [{"set no.": 1, "reps": 13, "weight": "11.13 kg"}, {"set no.": 2, "reps": 1, "weight": "11.22 kg"}, {"set no.": 3, "reps": 16, "weight": "10.05 kg"}, {"set no.": 4, "reps": 10, "weight": "10.80 kg"}], "dumbbell_fly": [{"set no.": 1, "reps": 15, "weight": "17.59 kg"}, {"set no.": 2, "reps": 17, "weight": "18.81 kg"}, {"set no.": 3, "reps": 17, "weight": "15.99 kg"}, {"set no.": 4, "reps": 17, "weight": "17.40 kg"}, {"set no.": 5, "reps": 8, "weight": "22.86 kg"}], "dumbbell_pullover": [{"set no.": 1, "reps": 18, "weight": "22.84 kg"}, {"set no.": 2, "reps": 15, "weight": "25.09 kg"}, {"set no.": 3, "reps": 13, "weight": "28.71 kg"}, {"set no.": 4, "reps": 4, "weight": "34.05 kg"}]}}