{"date": "2019-11-18", "split": "shoulders", "exercises": {"arnold_press": [{"set no.": 1, "reps": 2, "weight": "31.62 kg"}], "side_laterals": [{"set no.": 1, "reps": 15, "weight": "13.00 kg"}, {"set no.": 2, "reps": 9, "weight": "16.12 kg"}, {"set no.": 3, "reps": 11, "weight": "15.08 kg"}, {"set no.": 4, "reps": 16, "weight": "12.48 kg"}], "rear_laterals": [{"set no.": 1, "reps": 14, "weight": "5.41 kg"}], "cable_crossover": [{"set no.": 1, "reps": 12, "weight": "11.65 kg"}, {"set no.": 2, "reps": 17, "weight": "9.57 kg"}]}}