{"date": "2021-05-06", "split": "shoulders", "exercises": {"front_laterals": [{"set no.": 1, "reps": 18, "weight": "38.00 kg"}], "dumbbell_military_press": [{"set no.": 1, "reps": 8, "weight": "88.58 kg"}], "rear_laterals": [{"set no.": 1, "reps": 16, "weight": "16.58 kg"}, {"set no.": 2, "reps": 4, "weight": "24.88 kg"}, {"set no.": 3, "reps": 3, "weight": "25.60 kg"}, {"set no.": 4, "reps": 16, "weight": "16.58 kg"}, {"set no.": 5, "reps": 2, "weight": "26.22 kg"}], "cable_crossover": [{"set no.": 1, "reps": 8, "weight": "44.29 kg"}, {"set no.": 2, "reps": 20, "weight": "27.60 kg"}, {"set no.": 3, "reps": 18, "weight": "30.45 kg"}, {"set no.": 4, "reps": 19, "weight": "29.06 kg"}, {"set no.": 5, "reps": 20, "weight": "27.60 kg"}]}}