{"date": "2020-09-04", "split": "shoulders", "exercises": {"cable_crossover": [{"set no.": 1, "reps": 1, "weight": "12.36 kg"}, {"set no.": 2, "reps": 1, "weight": "12.36 kg"}, {"set no.": 3, "reps": 7, "weight": "11.16 kg"}, {"set no.": 4, "reps": 7, "weight": "11.16 kg"}, {"set no.": 5, "reps": 10, "weight": "10.56 kg"}, {"set no.": 6, "reps": 4, "weight": "11.76 kg"}], "rear_laterals": [{"set no.": 1, "reps": 3, "weight": "8.26 kg"}, {"set no.": 2, "reps": 1, "weight": "8.46 kg"}, {"set no.": 3, "reps": 4, "weight": "8.16 kg"}, {"set no.": 4, "reps": 9, "weight": "7.66 kg"}, {"set no.": 5, "reps": 8, "weight": "7.76 kg"}]}}