{"date": "2020-08-19", "split": "legs", "exercises": {"squat": [{"set no.": 1, "reps": 10, "weight": "112.50 kg"}], "deadlift": [{"set no.": 1, "reps": 13, "weight": "102.87 kg"}, {"set no.": 2, "reps": 8, "weight": "121.92 kg"}, {"set no.": 3, "reps": 2, "weight": "143.64 kg"}], "leg_extention": [{"set no.": 1, "reps": 13, "weight": "59.54 kg"}, {"set no.": 2, "reps": 16, "weight": "52.50 kg"}, {"set no.": 3, "reps": 2, "weight": "83.79 kg"}], "standing_calf_raise": [{"set no.": 1, "reps": 17, "weight": "21.74 kg"}, {"set no.": 2, "reps": 5, "weight": "33.34 kg"}, {"set no.": 3, "reps": 3, "weight": "34.69 kg"}, {"set no.": 4, "reps": 5, "weight": "33.34 kg"}], "barbell_lunge": [{"set no.": 1, "reps": 10, "weight": "65.63 kg"}, {"set no.": 2, "reps": 7, "weight": "72.77 kg"}, {"set no.": 3, "reps": 17, "weight": "51.12 kg"}, {"set no.": 4, "reps": 20, "weight": "44.10 kg"}]}}