{"date": "2019-06-02", "split": "back", "exercises": {"barbell shrug": [{"set no.": 1, "reps": 9, "weight": "12.45 kg"}], "face pull": [{"set no.": 1, "reps": 19, "weight": "5.33 kg"}, {"set no.": 2, "reps": 5, "weight": "8.24 kg"}, {"set no.": 3, "reps": 2, "weight": "8.73 kg"}, {"set no.": 4, "reps": 13, "weight": "6.22 kg"}], "lat pulldown": [{"set no.": 1, "reps": 14, "weight": "46.43 kg"}, {"set no.": 2, "reps": 9, "weight": "55.28 kg"}, {"set no.": 3, "reps": 18, "weight": "39.32 kg"}, {"set no.": 4, "reps": 16, "weight": "43.24 kg"}], "pullup": [{"set no.": 1, "reps": 15, "weight": "7.18 kg"}, {"set no.": 2, "reps": 1, "weight": "10.99 kg"}, {"set no.": 3, "reps": 5, "weight": "9.88 kg"}, {"set no.": 4, "reps": 15, "weight": "7.49 kg"}], "chinup": [{"set no.": 1, "reps": 12, "weight": "8.13 kg"}, {"set no.": 2, "reps": 3, "weight": "10.18 kg"}, {"set no.": 3, "reps": 16, "weight": "7.13 kg"}, {"set no.": 4, "reps": 16, "weight": "7.03 kg"}, {"set no.": 5, "reps": 19, "weight": "6.38 kg"}], "seated row": [{"set no.": 1, "reps": 14, "weight": "46.74 kg"}, {"set no.": 2, "reps": 8, "weight": "56.82 kg"}, {"set no.": 3, "reps": 6, "weight": "60.63 kg"}, {"set no.": 4, "reps": 7, "weight": "58.78 kg"}, {"set no.": 5, "reps": 11, "weight": "51.88 kg"}, {"set no.": 6, "reps": 19, "weight": "37.78 kg"}]}}