{"date": "2021-12-12", "split": "legs", "exercises": {"seated calf raise": [{"set no.": 1, "reps": 14, "weight": "16.453999999999976 kg"}], "standing calf raise": [{"set no.": 1, "reps": 8, "weight": "27.453999999999976 kg"}, {"set no.": 2, "reps": 16, "weight": "21.453999999999976 kg"}, {"set no.": 3, "reps": 20, "weight": "18.139999999999976 kg"}], "legpress": [{"set no.": 1, "reps": 3, "weight": "114.76799999999997 kg"}, {"set no.": 2, "reps": 14, "weight": "80.82599999999998 kg"}, {"set no.": 3, "reps": 12, "weight": "87.13999999999997 kg"}, {"set no.": 4, "reps": 12, "weight": "86.51199999999999 kg"}, {"set no.": 5, "reps": 3, "weight": "114.45399999999998 kg"}, {"set no.": 6, "reps": 11, "weight": "90.45399999999998 kg"}], "leg extention": [{"set no.": 1, "reps": 2, "weight": "69.01199999999999 kg"}, {"set no.": 2, "reps": 1, "weight": "71.70399999999998 kg"}, {"set no.": 3, "reps": 11, "weight": "53.57599999999998 kg"}, {"set no.": 4, "reps": 16, "weight": "44.51199999999998 kg"}], "deadlift": [{"set no.": 1, "reps": 13, "weight": "83.82599999999998 kg"}, {"set no.": 2, "reps": 13, "weight": "84.76799999999997 kg"}, {"set no.": 3, "reps": 8, "weight": "98.82599999999998 kg"}, {"set no.": 4, "reps": 5, "weight": "107.51199999999999 kg"}]}}