{"date": "2020-11-01", "split": "back", "exercises": {"face_pull": [{"set no.": 1, "reps": 12, "weight": "35.34 kg"}, {"set no.": 2, "reps": 9, "weight": "39.12 kg"}, {"set no.": 3, "reps": 16, "weight": "30.24 kg"}], "pullup": [{"set no.": 1, "reps": 20, "weight": "31.50 kg"}, {"set no.": 2, "reps": 6, "weight": "53.46 kg"}, {"set no.": 3, "reps": 14, "weight": "40.88 kg"}, {"set no.": 4, "reps": 19, "weight": "33.07 kg"}, {"set no.": 5, "reps": 4, "weight": "56.61 kg"}, {"set no.": 6, "reps": 14, "weight": "40.88 kg"}], "barbell_shrug": [{"set no.": 1, "reps": 14, "weight": "61.33 kg"}], "seated_row": [{"set no.": 1, "reps": 5, "weight": "385.87 kg"}, {"set no.": 2, "reps": 4, "weight": "396.27 kg"}, {"set no.": 3, "reps": 18, "weight": "242.93 kg"}]}}