{"date": "2020-10-05", "split": "chest", "exercises": {"dumbbell_pullover": [{"set no.": 1, "reps": 14, "weight": "23.89 kg"}, {"set no.": 2, "reps": 11, "weight": "25.41 kg"}, {"set no.": 3, "reps": 15, "weight": "23.14 kg"}, {"set no.": 4, "reps": 13, "weight": "23.18 kg"}, {"set no.": 5, "reps": 12, "weight": "23.93 kg"}, {"set no.": 6, "reps": 6, "weight": "28.79 kg"}], "barbell_incline_press": [{"set no.": 1, "reps": 8, "weight": "59.66 kg"}, {"set no.": 2, "reps": 16, "weight": "45.66 kg"}, {"set no.": 3, "reps": 4, "weight": "67.03 kg"}, {"set no.": 4, "reps": 14, "weight": "49.53 kg"}], "dip": [{"set no.": 1, "reps": 7, "weight": "8.15 kg"}], "dumbbell_fly": [{"set no.": 1, "reps": 5, "weight": "19.04 kg"}, {"set no.": 2, "reps": 16, "weight": "14.46 kg"}, {"set no.": 3, "reps": 4, "weight": "19.49 kg"}, {"set no.": 4, "reps": 11, "weight": "17.44 kg"}, {"set no.": 5, "reps": 13, "weight": "15.81 kg"}]}}