{"date": "2019-05-02", "split": "chest", "exercises": {"dumbbell fly": [{"set no.": 1, "reps": 14, "weight": "16.579999999999934 kg"}, {"set no.": 2, "reps": 7, "weight": "22.169999999999895 kg"}, {"set no.": 3, "reps": 5, "weight": "23.069999999999897 kg"}, {"set no.": 4, "reps": 7, "weight": "21.559999999999906 kg"}, {"set no.": 5, "reps": 17, "weight": "16.449999999999914 kg"}], "cable crossover": [{"set no.": 1, "reps": 17, "weight": "25.00499999999993 kg"}, {"set no.": 2, "reps": 18, "weight": "25.349999999999916 kg"}, {"set no.": 3, "reps": 2, "weight": "38.739999999999924 kg"}, {"set no.": 4, "reps": 8, "weight": "34.70999999999991 kg"}], "barbell incline press": [{"set no.": 1, "reps": 8, "weight": "62.099999999999916 kg"}], "dip": [{"set no.": 1, "reps": 20, "weight": "9.819999999999897 kg"}, {"set no.": 2, "reps": 12, "weight": "10.819999999999897 kg"}, {"set no.": 3, "reps": 6, "weight": "10.349999999999914 kg"}]}}