{"date": "2018-08-19", "split": "back", "exercises": {"chinup": [{"set no.": 1, "reps": 7, "weight": "14.13 kg"}, {"set no.": 2, "reps": 1, "weight": "15.63 kg"}, {"set no.": 3, "reps": 3, "weight": "15.13 kg"}, {"set no.": 4, "reps": 10, "weight": "13.38 kg"}, {"set no.": 5, "reps": 3, "weight": "15.13 kg"}, {"set no.": 6, "reps": 1, "weight": "15.63 kg"}], "seated_row": [{"set no.": 1, "reps": 4, "weight": "68.88 kg"}, {"set no.": 2, "reps": 6, "weight": "65.38 kg"}, {"set no.": 3, "reps": 5, "weight": "67.13 kg"}, {"set no.": 4, "reps": 6, "weight": "65.38 kg"}, {"set no.": 5, "reps": 2, "weight": "72.38 kg"}]}}