{"date": "2018-08-10", "split": "chest", "exercises": {"dumbbell_pullover": [{"set no.": 1, "reps": 5, "weight": "31.43 kg"}, {"set no.": 2, "reps": 2, "weight": "33.68 kg"}, {"set no.": 3, "reps": 9, "weight": "28.43 kg"}, {"set no.": 4, "reps": 7, "weight": "29.93 kg"}], "dip": [{"set no.": 1, "reps": 5, "weight": "9.55 kg"}, {"set no.": 2, "reps": 8, "weight": "9.18 kg"}, {"set no.": 3, "reps": 4, "weight": "9.68 kg"}, {"set no.": 4, "reps": 8, "weight": "9.18 kg"}, {"set no.": 5, "reps": 6, "weight": "9.43 kg"}, {"set no.": 6, "reps": 7, "weight": "9.30 kg"}], "cable_crossover": [{"set no.": 1, "reps": 7, "weight": "34.05 kg"}, {"set no.": 2, "reps": 9, "weight": "32.30 kg"}, {"set no.": 3, "reps": 5, "weight": "35.80 kg"}, {"set no.": 4, "reps": 2, "weight": "38.43 kg"}], "barbell_incline_press": [{"set no.": 1, "reps": 9, "weight": "59.43 kg"}, {"set no.": 2, "reps": 10, "weight": "57.68 kg"}], "barbell_bench_press": [{"set no.": 1, "reps": 5, "weight": "83.93 kg"}, {"set no.": 2, "reps": 1, "weight": "92.93 kg"}], "dumbbell_fly": [{"set no.": 1, "reps": 1, "weight": "22.73 kg"}, {"set no.": 2, "reps": 2, "weight": "22.28 kg"}, {"set no.": 3, "reps": 7, "weight": "20.03 kg"}]}}