{"date": "2018-08-08", "split": "chest", "exercises": {"barbell_incline_press": [{"set no.": 1, "reps": 5, "weight": "67.24 kg"}], "dumbbell_fly": [{"set no.": 1, "reps": 6, "weight": "21.29 kg"}, {"set no.": 2, "reps": 10, "weight": "19.49 kg"}, {"set no.": 3, "reps": 6, "weight": "21.29 kg"}, {"set no.": 4, "reps": 5, "weight": "21.74 kg"}, {"set no.": 5, "reps": 3, "weight": "22.64 kg"}, {"set no.": 6, "reps": 4, "weight": "22.19 kg"}], "barbell_bench_press": [{"set no.": 1, "reps": 3, "weight": "89.24 kg"}, {"set no.": 2, "reps": 5, "weight": "84.74 kg"}, {"set no.": 3, "reps": 2, "weight": "91.49 kg"}], "dip": [{"set no.": 1, "reps": 9, "weight": "9.87 kg"}, {"set no.": 2, "reps": 5, "weight": "10.37 kg"}]}}