{"date": "2020-02-18", "split": "shoulders", "exercises": {"arnold press": [{"set no.": 1, "reps": 12, "weight": "15.52 kg"}, {"set no.": 2, "reps": 15, "weight": "15.40 kg"}, {"set no.": 3, "reps": 12, "weight": "17.68 kg"}, {"set no.": 4, "reps": 17, "weight": "15.68 kg"}], "side laterals": [{"set no.": 1, "reps": 19, "weight": "11.73 kg"}, {"set no.": 2, "reps": 1, "weight": "14.61 kg"}, {"set no.": 3, "reps": 16, "weight": "10.32 kg"}, {"set no.": 4, "reps": 4, "weight": "15.48 kg"}, {"set no.": 5, "reps": 19, "weight": "11.73 kg"}], "cable crossover": [{"set no.": 1, "reps": 6, "weight": "11.66 kg"}, {"set no.": 2, "reps": 13, "weight": "10.80 kg"}, {"set no.": 3, "reps": 17, "weight": "8.92 kg"}, {"set no.": 4, "reps": 7, "weight": "13.08 kg"}, {"set no.": 5, "reps": 6, "weight": "12.74 kg"}]}}