{"date": "2019-04-11", "split": "chest", "exercises": {"dumbbell fly": [{"set no.": 1, "reps": 18, "weight": "12.02 kg"}, {"set no.": 2, "reps": 6, "weight": "18.13 kg"}, {"set no.": 3, "reps": 1, "weight": "19.44 kg"}, {"set no.": 4, "reps": 3, "weight": "18.77 kg"}], "cable crossover": [{"set no.": 1, "reps": 11, "weight": "27.50 kg"}, {"set no.": 2, "reps": 9, "weight": "29.72 kg"}, {"set no.": 3, "reps": 7, "weight": "30.76 kg"}], "barbell bench press": [{"set no.": 1, "reps": 14, "weight": "60.62 kg"}, {"set no.": 2, "reps": 16, "weight": "56.12 kg"}], "barbell incline press": [{"set no.": 1, "reps": 2, "weight": "69.33 kg"}, {"set no.": 2, "reps": 16, "weight": "44.12 kg"}, {"set no.": 3, "reps": 4, "weight": "65.83 kg"}, {"set no.": 4, "reps": 1, "weight": "71.08 kg"}]}}