{"date": "2019-11-25", "split": "back", "exercises": {"lat_pulldown": [{"set no.": 1, "reps": 17, "weight": "40.51 kg"}, {"set no.": 2, "reps": 20, "weight": "35.36 kg"}], "chinup": [{"set no.": 1, "reps": 4, "weight": "9.40 kg"}, {"set no.": 2, "reps": 2, "weight": "9.76 kg"}, {"set no.": 3, "reps": 1, "weight": "10.08 kg"}, {"set no.": 4, "reps": 3, "weight": "9.55 kg"}], "barbell_shrug": [{"set no.": 1, "reps": 10, "weight": "11.58 kg"}, {"set no.": 2, "reps": 7, "weight": "12.74 kg"}, {"set no.": 3, "reps": 17, "weight": "8.89 kg"}, {"set no.": 4, "reps": 5, "weight": "13.52 kg"}, {"set no.": 5, "reps": 14, "weight": "10.08 kg"}]}}