{"date": "2019-08-18", "split": "back", "exercises": {"barbell_shrug": [{"set no.": 1, "reps": 4, "weight": "18.44 kg"}], "face_pull": [{"set no.": 1, "reps": 1, "weight": "12.74 kg"}, {"set no.": 2, "reps": 2, "weight": "12.54 kg"}], "pullup": [{"set no.": 1, "reps": 5, "weight": "13.69 kg"}, {"set no.": 2, "reps": 4, "weight": "13.94 kg"}, {"set no.": 3, "reps": 9, "weight": "12.69 kg"}, {"set no.": 4, "reps": 7, "weight": "13.19 kg"}], "chinup": [{"set no.": 1, "reps": 7, "weight": "13.19 kg"}, {"set no.": 2, "reps": 7, "weight": "13.19 kg"}]}}