{"date": "2020-06-22", "split": "shoulders", "exercises": {"front laterals": [{"set no.": 1, "reps": 9, "weight": "15.68 kg"}, {"set no.": 2, "reps": 1, "weight": "17.68 kg"}, {"set no.": 3, "reps": 11, "weight": "15.18 kg"}, {"set no.": 4, "reps": 17, "weight": "13.02 kg"}, {"set no.": 5, "reps": 6, "weight": "16.43 kg"}], "side laterals": [{"set no.": 1, "reps": 1, "weight": "15.70 kg"}, {"set no.": 2, "reps": 18, "weight": "11.45 kg"}, {"set no.": 3, "reps": 17, "weight": "12.36 kg"}, {"set no.": 4, "reps": 11, "weight": "15.18 kg"}], "dumbbell military press": [{"set no.": 1, "reps": 11, "weight": "18.21 kg"}, {"set no.": 2, "reps": 3, "weight": "20.09 kg"}, {"set no.": 3, "reps": 12, "weight": "16.49 kg"}, {"set no.": 4, "reps": 10, "weight": "17.29 kg"}], "cable crossover": [{"set no.": 1, "reps": 12, "weight": "11.55 kg"}, {"set no.": 2, "reps": 20, "weight": "11.27 kg"}], "rear laterals": [{"set no.": 1, "reps": 11, "weight": "10.17 kg"}, {"set no.": 2, "reps": 16, "weight": "7.69 kg"}]}}