{"date": "2019-01-29", "split": "chest", "exercises": {"dip": [{"set no.": 1, "reps": 2, "weight": "7.746999999999976 kg"}, {"set no.": 2, "reps": 14, "weight": "7.245999999999968 kg"}, {"set no.": 3, "reps": 14, "weight": "6.91299999999997 kg"}, {"set no.": 4, "reps": 9, "weight": "7.53799999999997 kg"}, {"set no.": 5, "reps": 14, "weight": "6.579999999999973 kg"}, {"set no.": 6, "reps": 12, "weight": "6.829999999999973 kg"}], "dumbbell pullover": [{"set no.": 1, "reps": 5, "weight": "29.579999999999973 kg"}, {"set no.": 2, "reps": 2, "weight": "31.496999999999975 kg"}, {"set no.": 3, "reps": 2, "weight": "32.16299999999997 kg"}, {"set no.": 4, "reps": 2, "weight": "31.496999999999975 kg"}, {"set no.": 5, "reps": 5, "weight": "30.245999999999967 kg"}, {"set no.": 6, "reps": 7, "weight": "28.412999999999972 kg"}]}}