{"date": "2019-06-05", "split": "legs", "exercises": {"hamstring curl": [{"set no.": 1, "reps": 10, "weight": "34.102 kg"}, {"set no.": 2, "reps": 13, "weight": "30.771000000000004 kg"}, {"set no.": 3, "reps": 20, "weight": "22.852 kg"}, {"set no.": 4, "reps": 13, "weight": "30.903000000000002 kg"}, {"set no.": 5, "reps": 20, "weight": "23.028 kg"}], "standing calf raise": [{"set no.": 1, "reps": 1, "weight": "29.778 kg"}, {"set no.": 2, "reps": 1, "weight": "29.69 kg"}, {"set no.": 3, "reps": 19, "weight": "16.146 kg"}, {"set no.": 4, "reps": 12, "weight": "21.352 kg"}], "seated calf raise": [{"set no.": 1, "reps": 7, "weight": "16.984 kg"}]}}