{"date": "2019-06-05", "split": "back", "exercises": {"seated_row": [{"set no.": 1, "reps": 18, "weight": "169.78 kg"}], "lat_pulldown": [{"set no.": 1, "reps": 20, "weight": "154.35 kg"}, {"set no.": 2, "reps": 5, "weight": "270.11 kg"}, {"set no.": 3, "reps": 7, "weight": "254.68 kg"}], "pullup": [{"set no.": 1, "reps": 7, "weight": "36.38 kg"}, {"set no.": 2, "reps": 17, "weight": "25.36 kg"}, {"set no.": 3, "reps": 6, "weight": "37.48 kg"}], "face_pull": [{"set no.": 1, "reps": 19, "weight": "18.52 kg"}, {"set no.": 2, "reps": 10, "weight": "26.46 kg"}, {"set no.": 3, "reps": 17, "weight": "20.29 kg"}, {"set no.": 4, "reps": 11, "weight": "25.58 kg"}, {"set no.": 5, "reps": 4, "weight": "31.75 kg"}], "barbell_shrug": [{"set no.": 1, "reps": 18, "weight": "36.38 kg"}, {"set no.": 2, "reps": 11, "weight": "47.96 kg"}, {"set no.": 3, "reps": 9, "weight": "51.27 kg"}, {"set no.": 4, "reps": 7, "weight": "54.57 kg"}, {"set no.": 5, "reps": 10, "weight": "49.61 kg"}], "chinup": [{"set no.": 1, "reps": 17, "weight": "25.36 kg"}, {"set no.": 2, "reps": 5, "weight": "38.59 kg"}]}}