{"date": "2019-05-09", "split": "legs", "exercises": {"squat": [{"set no.": 1, "reps": 11, "weight": "93.16999999999992 kg"}, {"set no.": 2, "reps": 3, "weight": "116.55299999999993 kg"}, {"set no.": 3, "reps": 15, "weight": "81.7869999999999 kg"}, {"set no.": 4, "reps": 20, "weight": "67.4039999999999 kg"}], "leg extention": [{"set no.": 1, "reps": 2, "weight": "73.9039999999999 kg"}, {"set no.": 2, "reps": 2, "weight": "73.2869999999999 kg"}, {"set no.": 3, "reps": 5, "weight": "66.80299999999993 kg"}, {"set no.": 4, "reps": 14, "weight": "52.28699999999991 kg"}], "deadlift": [{"set no.": 1, "reps": 9, "weight": "99.7869999999999 kg"}, {"set no.": 2, "reps": 13, "weight": "87.16999999999992 kg"}, {"set no.": 3, "reps": 16, "weight": "78.16999999999992 kg"}, {"set no.": 4, "reps": 13, "weight": "87.7869999999999 kg"}], "legpress": [{"set no.": 1, "reps": 9, "weight": "98.55299999999993 kg"}, {"set no.": 2, "reps": 2, "weight": "121.4039999999999 kg"}, {"set no.": 3, "reps": 18, "weight": "72.16999999999992 kg"}, {"set no.": 4, "reps": 7, "weight": "105.7869999999999 kg"}], "standing calf raise": [{"set no.": 1, "reps": 19, "weight": "21.302999999999923 kg"}, {"set no.": 2, "reps": 17, "weight": "24.653999999999897 kg"}], "hamstring curl": [{"set no.": 1, "reps": 4, "weight": "45.43599999999993 kg"}]}}