{"date": "2019-06-23", "split": "shoulders", "exercises": {"front laterals": [{"set no.": 1, "reps": 10, "weight": "20.7 kg"}, {"set no.": 2, "reps": 1, "weight": "26.5 kg"}, {"set no.": 3, "reps": 13, "weight": "22.653846153846153 kg"}, {"set no.": 4, "reps": 13, "weight": "20.46153846153846 kg"}, {"set no.": 5, "reps": 2, "weight": "26.0 kg"}, {"set no.": 6, "reps": 17, "weight": "30.294117647058822 kg"}], "dumbbell military press": [{"set no.": 1, "reps": 17, "weight": "28.382352941176475 kg"}, {"set no.": 2, "reps": 15, "weight": "28.300000000000004 kg"}], "arnold press": [{"set no.": 1, "reps": 12, "weight": "21.0 kg"}, {"set no.": 2, "reps": 6, "weight": "24.0 kg"}], "side laterals": [{"set no.": 1, "reps": 19, "weight": "22.86842105263158 kg"}, {"set no.": 2, "reps": 8, "weight": "27.750000000000004 kg"}, {"set no.": 3, "reps": 20, "weight": "20.1 kg"}, {"set no.": 4, "reps": 20, "weight": "27.900000000000002 kg"}, {"set no.": 5, "reps": 11, "weight": "30.363636363636363 kg"}]}}