{"date": "2021-07-30", "split": "legs", "exercises": {"seated_calf_raise": [{"set no.": 1, "reps": 15, "weight": "17.56 kg"}], "standing_calf_raise": [{"set no.": 1, "reps": 12, "weight": "27.74 kg"}, {"set no.": 2, "reps": 9, "weight": "29.43 kg"}, {"set no.": 3, "reps": 3, "weight": "32.81 kg"}], "squat": [{"set no.": 1, "reps": 9, "weight": "98.06 kg"}, {"set no.": 2, "reps": 5, "weight": "109.50 kg"}, {"set no.": 3, "reps": 16, "weight": "78.18 kg"}, {"set no.": 4, "reps": 14, "weight": "82.50 kg"}]}}