{"date": "2020-02-12", "split": "legs", "exercises": {"seated calf raise": [{"set no.": 1, "reps": 2, "weight": "19.15 kg"}, {"set no.": 2, "reps": 13, "weight": "13.67 kg"}, {"set no.": 3, "reps": 9, "weight": "15.65 kg"}, {"set no.": 4, "reps": 7, "weight": "16.61 kg"}, {"set no.": 5, "reps": 20, "weight": "10.13 kg"}, {"set no.": 6, "reps": 15, "weight": "12.65 kg"}], "hamstring curl": [{"set no.": 1, "reps": 5, "weight": "39.49 kg"}, {"set no.": 2, "reps": 13, "weight": "30.52 kg"}, {"set no.": 3, "reps": 3, "weight": "41.79 kg"}, {"set no.": 4, "reps": 12, "weight": "31.63 kg"}], "legpress": [{"set no.": 1, "reps": 7, "weight": "99.11 kg"}, {"set no.": 2, "reps": 14, "weight": "78.13 kg"}, {"set no.": 3, "reps": 5, "weight": "105.17 kg"}]}}