{"date": "2020-07-31", "split": "back", "exercises": {"lat_pulldown": [{"set no.": 1, "reps": 8, "weight": "60.90 kg"}, {"set no.": 2, "reps": 5, "weight": "66.15 kg"}, {"set no.": 3, "reps": 2, "weight": "71.40 kg"}, {"set no.": 4, "reps": 8, "weight": "60.90 kg"}, {"set no.": 5, "reps": 13, "weight": "51.60 kg"}], "seated_row": [{"set no.": 1, "reps": 19, "weight": "43.28 kg"}], "pullup": [{"set no.": 1, "reps": 1, "weight": "16.28 kg"}, {"set no.": 2, "reps": 7, "weight": "12.60 kg"}, {"set no.": 3, "reps": 15, "weight": "11.15 kg"}], "barbell_shrug": [{"set no.": 1, "reps": 18, "weight": "12.60 kg"}, {"set no.": 2, "reps": 20, "weight": "12.94 kg"}, {"set no.": 3, "reps": 11, "weight": "17.40 kg"}]}}