{"date": "2019-03-08", "split": "chest", "exercises": {"cable_crossover": [{"set no.": 1, "reps": 15, "weight": "36.09 kg"}, {"set no.": 2, "reps": 10, "weight": "43.31 kg"}], "dip": [{"set no.": 1, "reps": 1, "weight": "8.14 kg"}, {"set no.": 2, "reps": 20, "weight": "4.13 kg"}, {"set no.": 3, "reps": 15, "weight": "5.16 kg"}, {"set no.": 4, "reps": 13, "weight": "5.57 kg"}, {"set no.": 5, "reps": 17, "weight": "4.77 kg"}], "dumbbell_fly": [{"set no.": 1, "reps": 3, "weight": "27.47 kg"}, {"set no.": 2, "reps": 10, "weight": "22.41 kg"}, {"set no.": 3, "reps": 4, "weight": "26.89 kg"}], "barbell_bench_press": [{"set no.": 1, "reps": 9, "weight": "115.79 kg"}, {"set no.": 2, "reps": 18, "weight": "82.67 kg"}, {"set no.": 3, "reps": 9, "weight": "115.09 kg"}], "dumbbell_pullover": [{"set no.": 1, "reps": 16, "weight": "30.06 kg"}, {"set no.": 2, "reps": 1, "weight": "48.26 kg"}, {"set no.": 3, "reps": 11, "weight": "36.11 kg"}]}}