{"date": "2020-03-04", "split": "legs", "exercises": {"hamstring_curl": [{"set no.": 1, "reps": 4, "weight": "311.85 kg"}, {"set no.": 2, "reps": 18, "weight": "190.57 kg"}, {"set no.": 3, "reps": 5, "weight": "303.58 kg"}, {"set no.": 4, "reps": 10, "weight": "259.87 kg"}], "barbell_lunge": [{"set no.": 1, "reps": 4, "weight": "485.10 kg"}, {"set no.": 2, "reps": 8, "weight": "431.20 kg"}, {"set no.": 3, "reps": 6, "weight": "457.55 kg"}, {"set no.": 4, "reps": 4, "weight": "485.73 kg"}, {"set no.": 5, "reps": 17, "weight": "309.92 kg"}, {"set no.": 6, "reps": 5, "weight": "472.24 kg"}]}}