{"date": "2020-12-21", "split": "shoulders", "exercises": {"rear_laterals": [{"set no.": 1, "reps": 10, "weight": "12.00 kg"}, {"set no.": 2, "reps": 4, "weight": "14.40 kg"}, {"set no.": 3, "reps": 7, "weight": "13.20 kg"}], "front_laterals": [{"set no.": 1, "reps": 11, "weight": "29.00 kg"}, {"set no.": 2, "reps": 2, "weight": "38.00 kg"}, {"set no.": 3, "reps": 1, "weight": "39.00 kg"}], "side_laterals": [{"set no.": 1, "reps": 1, "weight": "39.00 kg"}, {"set no.": 2, "reps": 15, "weight": "25.00 kg"}, {"set no.": 3, "reps": 2, "weight": "38.00 kg"}, {"set no.": 4, "reps": 14, "weight": "26.00 kg"}], "dumbbell_military_press": [{"set no.": 1, "reps": 15, "weight": "40.00 kg"}, {"set no.": 2, "reps": 20, "weight": "32.00 kg"}], "cable_crossover": [{"set no.": 1, "reps": 18, "weight": "17.60 kg"}, {"set no.": 2, "reps": 5, "weight": "28.00 kg"}, {"set no.": 3, "reps": 17, "weight": "18.40 kg"}, {"set no.": 4, "reps": 6, "weight": "27.20 kg"}, {"set no.": 5, "reps": 11, "weight": "23.20 kg"}], "arnold_press": [{"set no.": 1, "reps": 6, "weight": "54.40 kg"}]}}