{"date": "2019-06-14", "split": "shoulders", "exercises": {"arnold_press": [{"set no.": 1, "reps": 18, "weight": "68.11 kg"}], "front_laterals": [{"set no.": 1, "reps": 9, "weight": "59.98 kg"}, {"set no.": 2, "reps": 9, "weight": "59.98 kg"}], "dumbbell_military_press": [{"set no.": 1, "reps": 10, "weight": "92.88 kg"}], "cable_crossover": [{"set no.": 1, "reps": 7, "weight": "51.08 kg"}, {"set no.": 2, "reps": 19, "weight": "32.51 kg"}, {"set no.": 3, "reps": 1, "weight": "60.37 kg"}, {"set no.": 4, "reps": 1, "weight": "60.37 kg"}, {"set no.": 5, "reps": 10, "weight": "46.44 kg"}], "rear_laterals": [{"set no.": 1, "reps": 9, "weight": "23.99 kg"}, {"set no.": 2, "reps": 20, "weight": "15.48 kg"}, {"set no.": 3, "reps": 16, "weight": "18.58 kg"}, {"set no.": 4, "reps": 14, "weight": "20.12 kg"}, {"set no.": 5, "reps": 3, "weight": "28.64 kg"}], "side_laterals": [{"set no.": 1, "reps": 15, "weight": "48.37 kg"}, {"set no.": 2, "reps": 9, "weight": "59.98 kg"}, {"set no.": 3, "reps": 6, "weight": "65.79 kg"}, {"set no.": 4, "reps": 1, "weight": "75.46 kg"}, {"set no.": 5, "reps": 3, "weight": "71.59 kg"}]}}