{"date": "2020-02-16", "split": "legs", "exercises": {"legpress": [{"set no.": 1, "reps": 20, "weight": "143.5 kg"}, {"set no.": 2, "reps": 16, "weight": "144.0625 kg"}, {"set no.": 3, "reps": 7, "weight": "165.14285714285714 kg"}], "seated calf raise": [{"set no.": 1, "reps": 4, "weight": "154.25 kg"}, {"set no.": 2, "reps": 4, "weight": "129.75 kg"}], "hamstring curl": [{"set no.": 1, "reps": 2, "weight": "135.0 kg"}, {"set no.": 2, "reps": 13, "weight": "115.51923076923077 kg"}, {"set no.": 3, "reps": 20, "weight": "128.05 kg"}, {"set no.": 4, "reps": 3, "weight": "112.33333333333333 kg"}, {"set no.": 5, "reps": 9, "weight": "130.05555555555554 kg"}, {"set no.": 6, "reps": 9, "weight": "129.61111111111111 kg"}], "deadlift": [{"set no.": 1, "reps": 11, "weight": "162.0909090909091 kg"}, {"set no.": 2, "reps": 5, "weight": "134.75 kg"}, {"set no.": 3, "reps": 11, "weight": "121.75 kg"}, {"set no.": 4, "reps": 5, "weight": "161.05 kg"}, {"set no.": 5, "reps": 6, "weight": "165.16666666666666 kg"}, {"set no.": 6, "reps": 9, "weight": "108.33333333333333 kg"}], "standing calf raise": [{"set no.": 1, "reps": 12, "weight": "128.0 kg"}, {"set no.": 2, "reps": 5, "weight": "103.8 kg"}, {"set no.": 3, "reps": 1, "weight": "124.75 kg"}]}}