{"date": "2019-07-30", "split": "back", "exercises": {"barbell_shrug": [{"set no.": 1, "reps": 8, "weight": "17.41 kg"}, {"set no.": 2, "reps": 7, "weight": "17.79 kg"}, {"set no.": 3, "reps": 6, "weight": "18.16 kg"}, {"set no.": 4, "reps": 6, "weight": "18.16 kg"}, {"set no.": 5, "reps": 9, "weight": "17.04 kg"}], "lat_pulldown": [{"set no.": 1, "reps": 6, "weight": "64.91 kg"}], "chinup": [{"set no.": 1, "reps": 10, "weight": "12.91 kg"}, {"set no.": 2, "reps": 2, "weight": "14.91 kg"}, {"set no.": 3, "reps": 6, "weight": "13.91 kg"}]}}