{"date": "2019-11-07", "split": "back", "exercises": {"lat pulldown": [{"set no.": 1, "reps": 19, "weight": "40.13999999999997 kg"}, {"set no.": 2, "reps": 17, "weight": "44.31799999999997 kg"}, {"set no.": 3, "reps": 12, "weight": "52.72899999999997 kg"}], "face pull": [{"set no.": 1, "reps": 13, "weight": "9.467999999999966 kg"}, {"set no.": 2, "reps": 20, "weight": "7.050999999999974 kg"}, {"set no.": 3, "reps": 6, "weight": "10.189999999999971 kg"}, {"set no.": 4, "reps": 15, "weight": "9.067999999999966 kg"}, {"set no.": 5, "reps": 8, "weight": "9.450999999999976 kg"}, {"set no.": 6, "reps": 8, "weight": "9.789999999999973 kg"}], "seated row": [{"set no.": 1, "reps": 12, "weight": "52.05099999999997 kg"}, {"set no.": 2, "reps": 6, "weight": "62.211999999999975 kg"}, {"set no.": 3, "reps": 19, "weight": "39.461999999999975 kg"}]}}