{"date": "2021-01-20", "split": "shoulders", "exercises": {"side_laterals": [{"set no.": 1, "reps": 16, "weight": "7.32 kg"}, {"set no.": 2, "reps": 15, "weight": "7.21 kg"}, {"set no.": 3, "reps": 4, "weight": "10.08 kg"}, {"set no.": 4, "reps": 5, "weight": "9.95 kg"}, {"set no.": 5, "reps": 15, "weight": "7.33 kg"}, {"set no.": 6, "reps": 6, "weight": "9.82 kg"}], "front_laterals": [{"set no.": 1, "reps": 19, "weight": "6.45 kg"}, {"set no.": 2, "reps": 16, "weight": "7.32 kg"}, {"set no.": 3, "reps": 1, "weight": "11.07 kg"}, {"set no.": 4, "reps": 1, "weight": "11.07 kg"}, {"set no.": 5, "reps": 15, "weight": "7.21 kg"}], "dumbbell_military_press": [{"set no.": 1, "reps": 12, "weight": "12.16 kg"}, {"set no.": 2, "reps": 15, "weight": "11.08 kg"}, {"set no.": 3, "reps": 20, "weight": "9.44 kg"}], "arnold_press": [{"set no.": 1, "reps": 14, "weight": "11.48 kg"}, {"set no.": 2, "reps": 6, "weight": "14.68 kg"}]}}