{
  "date": "2021-12-15",
  "split": "back_and_biceps",
  "exercises": {
    "pullup_wide_grip": [
      { "set no.": 1, "reps": 5, "weight": "0 kg" },
      { "set no.": 2, "reps": 5, "weight": "0 kg" },
      { "set no.": 3, "reps": 6, "weight": "0 kg" }
    ],
    "chinup": [
      { "set no.": 1, "reps": 5, "weight": "0 kg" },
      { "set no.": 2, "reps": 5, "weight": "0 kg" }
    ],
    "dead_row": [
      { "set no.": 1, "reps": 10, "weight": "40 kg" },
      { "set no.": 2, "reps": 10, "weight": "40 kg" }
    ],
    "lat_pulldown_with_twist": [
      { "set no.": 1, "reps": 10, "weight": "45 kg" },
      { "set no.": 2, "reps": 10, "weight": "45 kg" }
    ],
    "high_single_arm_cable_row": [
      { "set no.": 1, "reps": 10, "weight": "32 kg" },
      { "set no.": 2, "reps": 10, "weight": "32 kg" }
    ],
    "face_pull": [
      { "set no.": 1, "reps": 10, "weight": "9 kg" },
      { "set no.": 2, "reps": 10, "weight": "14 kg" }
    ],
    "dumbbell_pullover": [
      { "set no.": 1, "reps": 10, "weight": "24 kg" },
      { "set no.": 2, "reps": 5, "weight": "24 kg" }
    ],
    "lat_pulldown": [
      { "set no.": 1, "reps": 12, "weight": "32 kg" },
      { "set no.": 2, "reps": 12, "weight": "36 kg" }
    ],
    "diverging_low_row": [
      { "set no.": 1, "reps": 12, "weight": "45 kg" },
      { "set no.": 2, "reps": 12, "weight": "45 kg" }
    ],
    "EZ_bar_curl": [
      { "set no.": 1, "reps": 7, "weight": "40 kg" },
      { "set no.": 2, "reps": 10, "weight": "30 kg" }
    ]
  }
}
